fcapsy/__init__.py
fcapsy/basic_level.py
fcapsy/cohesion.py
fcapsy/similarity.py
fcapsy/typicality.py
fcapsy-0.3.0a1.dist-info/AUTHORS.md
fcapsy-0.3.0a1.dist-info/LICENSE
fcapsy-0.3.0a1.dist-info/METADATA
fcapsy-0.3.0a1.dist-info/WHEEL
fcapsy-0.3.0a1.dist-info/top_level.txt
fcapsy-0.3.0a1.dist-info/RECORD
