Metadata-Version: 2.1
Name: fcapsy
Version: 0.3.0a1
Summary: Experimental implementations of psychological phenomena (e.g. typicality, basic level) in FCA framework
Home-page: https://github.com/mikulatomas/fcapsy
Author: Tomáš Mikula
Author-email: mail@tomasmikula.cz
License: MIT license
Download-URL: https://github.com/mikulatomas/fcapsy/archive/v0.3.0a1.tar.gz
Keywords: fca formal concept analysis psychology cognition typicality basic-level
Platform: UNKNOWN
Classifier: Development Status :: 3 - Alpha
Classifier: Intended Audience :: Science/Research
Classifier: License :: OSI Approved :: MIT License
Classifier: Natural Language :: English
Classifier: Programming Language :: Python :: 3
Classifier: Programming Language :: Python :: 3.6
Classifier: Programming Language :: Python :: 3.7
Classifier: Programming Language :: Python :: 3.8
Classifier: Programming Language :: Python :: 3.9
Requires-Python: >=3.6
License-File: LICENSE
License-File: AUTHORS.md
Requires-Dist: concepts
Provides-Extra: dev
Requires-Dist: tox (>=3) ; extra == 'dev'
Requires-Dist: flake8 ; extra == 'dev'
Requires-Dist: pep8-naming ; extra == 'dev'
Requires-Dist: wheel ; extra == 'dev'
Requires-Dist: twine ; extra == 'dev'
Provides-Extra: test
Requires-Dist: pytest (>=6) ; extra == 'test'
Requires-Dist: pytest-cov ; extra == 'test'
